kahi_staff_affiliations/Kahi_staff_affiliations.py
kahi_staff_affiliations/__init__.py
kahi_staff_affiliations/_version.py
Kahi_staff_affiliations-0.1.2b0.dist-info/LICENSE
Kahi_staff_affiliations-0.1.2b0.dist-info/METADATA
Kahi_staff_affiliations-0.1.2b0.dist-info/WHEEL
Kahi_staff_affiliations-0.1.2b0.dist-info/top_level.txt
Kahi_staff_affiliations-0.1.2b0.dist-info/RECORD
